unexpectation_handler/__init__.py
unexpectation_handler/handler.py
unexpectation_handler/symbol.py
unexpectation_handler-1.0.2.dist-info/LICENSE
unexpectation_handler-1.0.2.dist-info/METADATA
unexpectation_handler-1.0.2.dist-info/WHEEL
unexpectation_handler-1.0.2.dist-info/RECORD
