Metadata-Version: 2.1
Name: unexpectation-handler
Version: 1.0.2
Summary: Never trust users! Encapsulate "isolating program vulnerabilities (errors, exceptions, or results due to unexpected input) that may be caused by executed code" and "calling function that handle them" as a package of Python.
Home-page: https://github.com/leoweyr/Python-Unexpectation_Handler
License: MIT
Author: leoweyr
Author-email: leoweyr@foxmail.com
Requires-Python: >=3.7,<4.0
Classifier: Development Status :: 3 - Alpha
Classifier: License :: OSI Approved :: MIT License
Classifier: Programming Language :: Python :: 3
Classifier: Programming Language :: Python :: 3.7
Classifier: Programming Language :: Python :: 3.8
Classifier: Programming Language :: Python :: 3.9
Classifier: Programming Language :: Python :: 3.10
Classifier: Programming Language :: Python :: 3.11
Project-URL: Repository, https://github.com/leoweyr/Python-Unexpectation_Handler
